<package>
  <description brief="Collection of algorithms for a general robot localization approach.">
      This involves data noise modeling, process and measurements model as well as filters for
      conventional state optimization problems.
  </description>
  <author>Javier Hidalgo Carrio/javier.hidalgo_carrio@dfki.de</author>

  <copyright>
    DFKI/robotik@dfki.de
    Javier Hidalgo Carrio/javier.hidalgo_carrio@dfki.de
  </copyright>

  <license>GPL v2 or later</license>

  <depend package="base/types" />
  <depend package="slam/mtk" />

</package>
